common/__init__.py
common/api_utils.py
common/auth_utils/__init__.py
common/auth_utils/auth_client.py
common/auth_utils/enums.py
common/auth_utils/interface_models.py
common/auth_utils/permissions.py
common/auth_utils/utils.py
common/aws_utils.py
common/config.py
common/core/__init__.py
common/core/utils.py
common/database/__init__.py
common/database/base_models.py
common/database/es_manager.py
common/database/exceptions.py
common/database/init_db.py
common/database/logging_models.py
common/database/search_model.py
common/database/session_manager.py
common/database/utility_models.py
common/database/utils.py
common/filestore/__init__.py
common/filestore/interface.py
common/filestore/local.py
common/filestore/s3.py
common/frontend_utils/__init__.py
common/frontend_utils/interface_models.py
common/intel/__init__.py
common/intel/bot.py
common/intel/functional.py
common/intel/repl.py
common/intel/utils.py
common/migrate_db.py
common/scheduling/__init__.py
common/scheduling/job_handler.py
common/scheduling/queue_utils.py
common/scheduling/utils.py
common/services.py
common/tasx_utils/__init__.py
common/tasx_utils/prompts/infer_service_metadata/v0.0.1.md
common/tasx_utils/prompts/infer_task_metadata/v0.0.1.md
common/tools/__init__.py
common/tools/tools.py
common/utils.py
tasc_common-0.0.4.dist-info/LICENSE
tasc_common-0.0.4.dist-info/METADATA
tasc_common-0.0.4.dist-info/WHEEL
tasc_common-0.0.4.dist-info/RECORD
