Metadata-Version: 2.3
Name: tasc-common
Version: 0.0.4
Summary: Shared utilities for the TASC-stack
Author: Nasim Rahaman
Author-email: nasim@tiptreesystems.com
Requires-Python: >=3.10,<3.14
Classifier: Programming Language :: Python :: 3
Classifier: Programming Language :: Python :: 3.10
Classifier: Programming Language :: Python :: 3.11
Classifier: Programming Language :: Python :: 3.12
Classifier: Programming Language :: Python :: 3.13
Requires-Dist: SQLAlchemy (>=2.0.29,<2.1.0)
Requires-Dist: aioboto3 (>=13.3.0,<13.4.0)
Requires-Dist: aiofiles (>=23.2.1,<24.0.0)
Requires-Dist: aiohttp (>=3.9.5,<4.0.0)
Requires-Dist: aioredis (>=2.0.1,<2.1.0)
Requires-Dist: alembic (>=1.12.1,<1.13.0)
Requires-Dist: annotated_types (>=0.7.0,<0.8.0)
Requires-Dist: asyncpg
Requires-Dist: backoff (>=2.2.1,<2.3.0)
Requires-Dist: boto3 (>=1.35.81,<1.36.0)
Requires-Dist: cryptography (>=42.0.0,<42.1.0)
Requires-Dist: diskcache (>=5.6.3,<5.7.0)
Requires-Dist: docstring_parser (>=0.16,<0.17)
Requires-Dist: fastapi (>=0.110.1,<0.111.0)
Requires-Dist: gitpython (>=3.1.24,<4.0.0)
Requires-Dist: httpx (>=0.28.1,<1.0.0)
Requires-Dist: jsonref (>=1.1.0,<2.0.0)
Requires-Dist: jsonschema (>=4.23.0,<4.24.0)
Requires-Dist: jwt (>=1.3.1,<1.4.0)
Requires-Dist: litellm (>=1.72.6,<1.73.0)
Requires-Dist: loguru (>=0.7.2,<0.8.0)
Requires-Dist: mistune (>=3.0.2,<3.1.0)
Requires-Dist: networkx (>=3.2.1,<3.3.0)
Requires-Dist: numpy (>=1.26.4,<1.27.0)
Requires-Dist: packaging (>=24.0,<24.1)
Requires-Dist: pandas (>=2.1.4,<2.2.0)
Requires-Dist: passlib[bcrypt] (>=1.7.4,<1.8.0)
Requires-Dist: pdfkit (>=1.0.0,<1.1.0)
Requires-Dist: pillow (>=10.3.0,<10.4.0)
Requires-Dist: psycopg2-binary (>=2.9.9,<3.0.0)
Requires-Dist: pydantic (>=2.7.0,<2.8.0)
Requires-Dist: pydantic_settings (>=2.2.1,<3.0.0)
Requires-Dist: python-dateutil (>=2.8.2,<3.0.0)
Requires-Dist: python-jose[cryptography] (>=3.3.0,<4.0.0)
Requires-Dist: requests (>=2.31.0,<2.32.0)
Requires-Dist: ruptures (>=1.1.9,<1.2.0)
Requires-Dist: sqlmodel (>=0.0.16,<0.1.0)
Requires-Dist: tenacity (>=8.2.2,<8.3.0)
Requires-Dist: tiktoken (>=0.7.0,<0.8.0)
Requires-Dist: uvicorn[standard] (>=0.29.0,<0.30.0)
Project-URL: Documentation, https://docs.tiptreesystems.com
